cattle_grid/__init__.py
cattle_grid/__main__.py
cattle_grid/alembic.ini
cattle_grid/processor.py
cattle_grid/py.typed
cattle_grid/statistics.py
cattle_grid/test_init.py
cattle_grid/version.py
cattle_grid/account/__init__.py
cattle_grid/account/account.py
cattle_grid/account/cli.py
cattle_grid/account/permissions.py
cattle_grid/account/rabbit.py
cattle_grid/account/test_account.py
cattle_grid/account/test_cli.py
cattle_grid/account/test_permissions.py
cattle_grid/account/test_rabbit.py
cattle_grid/account/processing/__init__.py
cattle_grid/account/processing/annotations.py
cattle_grid/account/processing/exception.py
cattle_grid/account/processing/history.py
cattle_grid/account/processing/info.py
cattle_grid/account/processing/router.py
cattle_grid/account/processing/schema.py
cattle_grid/account/processing/test_create_actor.py
cattle_grid/account/processing/test_exception.py
cattle_grid/account/processing/test_handlers.py
cattle_grid/account/processing/test_history.py
cattle_grid/account/processing/test_info.py
cattle_grid/account/processing/test_router.py
cattle_grid/account/processing/test_trigger.py
cattle_grid/account/processing/testing.py
cattle_grid/account/processing/trigger.py
cattle_grid/account/server/__init__.py
cattle_grid/account/server/account.py
cattle_grid/account/server/actor.py
cattle_grid/account/server/app.py
cattle_grid/account/server/dependencies.py
cattle_grid/account/server/responses.py
cattle_grid/account/server/streaming.py
cattle_grid/account/server/test_account.py
cattle_grid/account/server/test_actor.py
cattle_grid/account/server/test_signin.py
cattle_grid/account/server/test_streaming.py
cattle_grid/account/server/testing.py
cattle_grid/activity_pub/__init__.py
cattle_grid/activity_pub/activity.py
cattle_grid/activity_pub/enqueuer.py
cattle_grid/activity_pub/helper.py
cattle_grid/activity_pub/test_activity.py
cattle_grid/activity_pub/test_enqueuer.py
cattle_grid/activity_pub/actor/__init__.py
cattle_grid/activity_pub/actor/activity.py
cattle_grid-0.5.20.dist-info/METADATA
cattle_grid-0.5.20.dist-info/WHEEL
cattle_grid-0.5.20.dist-info/licenses/LICENSE
cattle_grid-0.5.20.dist-info/RECORD
