Metadata-Version: 2.4
Name: cattle_grid
Version: 0.5.20
Summary: Middleware for the Fediverse
License-File: LICENSE
Requires-Python: >=3.11
Requires-Dist: alembic>=1.17.2
Requires-Dist: argon2-cffi>=23.1.0
Requires-Dist: bovine>=0.5.13
Requires-Dist: dynaconf>=3.2.6
Requires-Dist: fastapi[standard]>=0.121.2
Requires-Dist: faststream[cli,rabbit]>=0.6.3
Requires-Dist: jinja2>=3.1.6
Requires-Dist: pydantic==2.12.2
Requires-Dist: sqlalchemy-utils>=0.41.2
Requires-Dist: sqlalchemy[asyncio]>=2.0.36
Requires-Dist: tomli-w>=1.0.0
Requires-Dist: uuid6>=2025.0.1
Provides-Extra: aiosqlite
Requires-Dist: aiosqlite>=0.21.0; extra == 'aiosqlite'
Provides-Extra: cache
Requires-Dist: fakeredis>=2.26.2; extra == 'cache'
Requires-Dist: redis>=5.2.1; extra == 'cache'
Provides-Extra: postgres
Requires-Dist: asyncpg>=0.30.0; extra == 'postgres'
Provides-Extra: uvicorn
Requires-Dist: uvicorn>=0.37.0; extra == 'uvicorn'
